<?xml version="1.0" encoding="UTF-8" ?>
<!DOCTYPE Entity SYSTEM "jbo_03_01.dtd">
<!---->
<Entity
  xmlns="http://xmlns.oracle.com/bc4j"
  Name="Users"
  Version="12.1.2.66.68"
  InheritPersonalization="merge"
  DBObjectType="table"
  DBObjectName="USERS"
  AliasName="Users"
  BindingStyle="OracleName">
  <Attribute
    Name="Id"
    IsNotNull="true"
    Precision="50"
    ColumnName="ID"
    SQLType="VARCHAR"
    Type="java.lang.String"
    ColumnType="VARCHAR2"
    TableName="USERS"
    PrimaryKey="true">
    <DesignTime>
      <Attr Name="_DisplaySize" Value="50"/>
    </DesignTime>
  </Attribute>
  <Attribute
    Name="FirstName"
    IsNotNull="true"
    Precision="50"
    ColumnName="FIRST_NAME"
    SQLType="VARCHAR"
    Type="java.lang.String"
    ColumnType="VARCHAR2"
    TableName="USERS">
    <DesignTime>
      <Attr Name="_DisplaySize" Value="50"/>
    </DesignTime>
  </Attribute>
  <Attribute
    Name="LastName"
    IsNotNull="true"
    Precision="50"
    ColumnName="LAST_NAME"
    SQLType="VARCHAR"
    Type="java.lang.String"
    ColumnType="VARCHAR2"
    TableName="USERS">
    <DesignTime>
      <Attr Name="_DisplaySize" Value="50"/>
    </DesignTime>
  </Attribute>
  <Attribute
    Name="Email"
    IsNotNull="true"
    Precision="100"
    ColumnName="EMAIL"
    SQLType="VARCHAR"
    Type="java.lang.String"
    ColumnType="VARCHAR2"
    TableName="USERS">
    <DesignTime>
      <Attr Name="_DisplaySize" Value="100"/>
    </DesignTime>
  </Attribute>
  <Attribute
    Name="IsAdmin"
    IsNotNull="true"
    Precision="1"
    Scale="0"
    ColumnName="IS_ADMIN"
    SQLType="NUMERIC"
    Type="java.lang.Integer"
    ColumnType="NUMBER"
    TableName="USERS"/>
  <Attribute
    Name="PassWd"
    IsNotNull="true"
    Precision="100"
    ColumnName="PASS_WD"
    SQLType="VARCHAR"
    Type="java.lang.String"
    ColumnType="VARCHAR2"
    TableName="USERS">
    <DesignTime>
      <Attr Name="_DisplaySize" Value="100"/>
    </DesignTime>
  </Attribute>
  <Attribute
    Name="Login"
    IsUnique="true"
    IsNotNull="true"
    Precision="30"
    ColumnName="LOGIN"
    SQLType="VARCHAR"
    Type="java.lang.String"
    ColumnType="VARCHAR2"
    TableName="USERS">
    <DesignTime>
      <Attr Name="_DisplaySize" Value="30"/>
    </DesignTime>
  </Attribute>
  <Attribute
    Name="Version"
    IsNotNull="true"
    ColumnName="VERSION"
    SQLType="TIMESTAMP"
    Type="java.sql.Timestamp"
    ColumnType="TIMESTAMP"
    TableName="USERS"/>
  <Attribute
    Name="Predefined"
    IsNotNull="true"
    Precision="1"
    Scale="0"
    ColumnName="PREDEFINED"
    SQLType="NUMERIC"
    Type="java.lang.Integer"
    ColumnType="NUMBER"
    TableName="USERS"/>
  <AccessorAttribute
    Name="Orders"
    Association="ua.divas.model.OrdersUsersFk1Assoc"
    AssociationEnd="ua.divas.model.OrdersUsersFk1Assoc.Orders"
    AssociationOtherEnd="ua.divas.model.OrdersUsersFk1Assoc.Users"
    Type="oracle.jbo.RowIterator"
    IsUpdateable="false"/>
  <AccessorAttribute
    Name="UsersGroups"
    Association="ua.divas.model.UsersGroupsFk2Assoc"
    AssociationEnd="ua.divas.model.UsersGroupsFk2Assoc.UsersGroups"
    AssociationOtherEnd="ua.divas.model.UsersGroupsFk2Assoc.Users"
    Type="oracle.jbo.RowIterator"
    IsUpdateable="false"/>
  <AccessorAttribute
    Name="UserSettings"
    Association="ua.divas.model.UserSettingsUsersFk1Assoc"
    AssociationEnd="ua.divas.model.UserSettingsUsersFk1Assoc.UserSettings"
    AssociationOtherEnd="ua.divas.model.UserSettingsUsersFk1Assoc.Users"
    Type="oracle.jbo.server.EntityImpl"
    IsUpdateable="true"/>
  <Key
    Name="UsersPk"
    PrimaryKey="true">
    <DesignTime>
      <Attr Name="_DBObjectName" Value="USERS_PK"/>
    </DesignTime>
    <AttrArray Name="Attributes">
      <Item Value="ua.divas.model.Users.Id"/>
    </AttrArray>
  </Key>
  <Key
    Name="UsersUk1">
    <DesignTime>
      <Attr Name="_isUnique" Value="true"/>
      <Attr Name="_DBObjectName" Value="USERS_UK1"/>
    </DesignTime>
    <AttrArray Name="Attributes">
      <Item Value="ua.divas.model.Users.Login"/>
    </AttrArray>
  </Key>
</Entity>
